gxps/__init__.py
gxps/canvas_tools.py
gxps/commands.py
gxps/config.py
gxps/control.py
gxps/controller.py
gxps/gui.py
gxps/io.py
gxps/main.py
gxps/models.py
gxps/processing.py
gxps/spectrum.py
gxps/state.py
gxps/utility.py
gxps/view.py
gxps/widgets.py
gxps/xdg.py
gxps-0.8.11.data/data/share/applications/com.github.schachmett.gxps.desktop
gxps-0.8.11.data/data/share/gxps/com.github.schachmett.gxps.desktop
gxps-0.8.11.data/data/share/gxps/assets/rsf.db
gxps-0.8.11.data/data/share/gxps/assets/icons/hicolor/128x128/gxps.png
gxps-0.8.11.data/data/share/gxps/assets/icons/hicolor/24x24/addpeak.png
gxps-0.8.11.data/data/share/gxps/assets/icons/hicolor/24x24/addregion.png
gxps-0.8.11.data/data/share/gxps/assets/icons/hicolor/24x24/atom_lib.png
gxps-0.8.11.data/data/share/gxps/assets/icons/hicolor/24x24/guesspeak.png
gxps-0.8.11.data/data/share/gxps/assets/icons/hicolor/24x24/pan.png
gxps-0.8.11.data/data/share/gxps/assets/icons/hicolor/24x24/removepeak.png
gxps-0.8.11.data/data/share/gxps/assets/icons/hicolor/24x24/removeregion.png
gxps-0.8.11.data/data/share/gxps/assets/icons/hicolor/256x256/gxps.png
gxps-0.8.11.data/data/share/gxps/assets/icons/hicolor/48x48/gxps.png
gxps-0.8.11.data/data/share/gxps/assets/icons/hicolor/512x512/gxps.png
gxps-0.8.11.data/data/share/gxps/assets/icons/hicolor/64x64/gxps.png
gxps-0.8.11.data/data/share/gxps/assets/icons/hicolor/96x96/gxps.png
gxps-0.8.11.data/data/share/gxps/assets/icons/hicolor/scalable/addregion.svg
gxps-0.8.11.data/data/share/gxps/assets/icons/hicolor/scalable/guesspeak.svg
gxps-0.8.11.data/data/share/gxps/assets/icons/hicolor/scalable/gxps.svg
gxps-0.8.11.data/data/share/gxps/assets/icons/hicolor/scalable/old_atom_lib.svg
gxps-0.8.11.data/data/share/gxps/assets/icons/hicolor/scalable/old_atom_lib_white.png
gxps-0.8.11.data/data/share/gxps/assets/icons/hicolor/scalable/old_pan.jpg
gxps-0.8.11.data/data/share/gxps/assets/icons/hicolor/scalable/removepeak.svg
gxps-0.8.11.dist-info/AUTHORS
gxps-0.8.11.dist-info/LICENSE
gxps-0.8.11.dist-info/METADATA
gxps-0.8.11.dist-info/WHEEL
gxps-0.8.11.dist-info/entry_points.txt
gxps-0.8.11.dist-info/pbr.json
gxps-0.8.11.dist-info/top_level.txt
gxps-0.8.11.dist-info/RECORD
